[
  {
    "id": "58e4f889-c18f-442b-b95d-c85a7fddc32c",
    "email": "example@gmail.com",
    "type": "weekly_review_view",
    "createdAt": "2026-04-07T01:45:35.864Z"
  },
  {
    "id": "b0375646-14b7-4d6c-a19c-b164b4ae7749",
    "email": "example@gmail.com",
    "type": "weekly_review_view",
    "createdAt": "2026-04-07T01:46:38.955Z"
  },
  {
    "id": "077862c6-10b8-495b-b063-c9125dca0f1e",
    "email": "example@gmail.com",
    "type": "weekly_review_view",
    "createdAt": "2026-04-07T02:00:05.850Z"
  },
  {
    "id": "f6fd4d59-e062-45e3-a340-5885e2097067",
    "email": "example@gmail.com",
    "type": "weekly_review_view",
    "createdAt": "2026-04-07T02:00:32.683Z"
  },
  {
    "id": "2b6396fb-0089-4dee-a4c6-61f0a6a0f236",
    "email": "example@gmail.com",
    "type": "weekly_review_view",
    "createdAt": "2026-04-07T02:00:32.735Z"
  },
  {
    "id": "59360c44-b8cf-432f-900e-d99877c6eb92",
    "email": "example@gmail.com",
    "type": "weekly_review_view",
    "createdAt": "2026-04-07T02:18:42.882Z"
  },
  {
    "id": "ce01cd9b-cf66-46a2-bea6-9c16bec48316",
    "email": "example@gmail.com",
    "type": "weekly_review_view",
    "createdAt": "2026-04-07T02:18:43.995Z"
  },
  {
    "id": "e2ff805e-cabb-4488-9ec7-603d003d8a54",
    "email": "example@gmail.com",
    "type": "weekly_review_view",
    "createdAt": "2026-04-07T02:18:46.428Z"
  },
  {
    "id": "ed583c4e-975d-4de8-86a3-15ecc72b7855",
    "email": "example@gmail.com",
    "type": "weekly_review_view",
    "createdAt": "2026-04-07T02:18:47.899Z"
  },
  {
    "id": "c0804226-49a1-4982-8b79-d8591086e901",
    "email": "example@gmail.com",
    "type": "weekly_review_view",
    "createdAt": "2026-04-07T02:18:51.231Z"
  },
  {
    "id": "848a3b3e-d2e5-4f13-868e-a94679e90836",
    "email": "example@gmail.com",
    "type": "weekly_review_view",
    "createdAt": "2026-04-07T02:18:52.450Z"
  },
  {
    "id": "c3b575dc-f353-4102-a974-e921aeaf10d9",
    "email": "example@gmail.com",
    "type": "weekly_review_view",
    "createdAt": "2026-04-07T02:26:21.636Z"
  },
  {
    "id": "3f9e2a37-2c52-4cc0-90b2-97c3c1a538f0",
    "email": "example@gmail.com",
    "type": "weekly_review_view",
    "createdAt": "2026-04-07T02:40:13.494Z"
  },
  {
    "id": "5eda49d1-472c-47d6-9bbc-e9a95a0b13e4",
    "email": "example@gmail.com",
    "type": "weekly_review_view",
    "createdAt": "2026-04-07T02:40:15.578Z"
  },
  {
    "id": "465fc0c0-251e-40ce-8b95-c094d148c963",
    "email": "example@gmail.com",
    "type": "weekly_review_view",
    "createdAt": "2026-04-07T02:42:20.575Z"
  },
  {
    "id": "0f992ce6-608c-4ffb-a633-b39970dce6d6",
    "email": "example@gmail.com",
    "type": "weekly_review_view",
    "createdAt": "2026-04-07T02:43:37.391Z"
  },
  {
    "id": "e57f88f9-eb1f-4bcb-ac02-a9c9db25d6a2",
    "email": "example@gmail.com",
    "type": "weekly_review_view",
    "createdAt": "2026-04-07T02:55:23.396Z"
  },
  {
    "id": "fee7380d-47d3-429d-a362-1a11b6d999fe",
    "email": "example@gmail.com",
    "type": "weekly_review_view",
    "createdAt": "2026-04-08T01:44:25.171Z"
  },
  {
    "id": "180dcb64-76b7-4536-a679-cef07190c6fe",
    "email": "example@gmail.com",
    "type": "weekly_review_view",
    "createdAt": "2026-04-14T01:56:21.142Z"
  },
  {
    "id": "8934e8c9-c8d2-4270-9d39-d5d895d18f81",
    "email": "example@gmail.com",
    "type": "weekly_review_view",
    "createdAt": "2026-04-14T01:56:24.788Z"
  },
  {
    "id": "28939a99-b075-465a-83b4-f08922c64239",
    "email": "example@gmail.com",
    "type": "weekly_review_view",
    "createdAt": "2026-04-14T02:25:16.598Z"
  },
  {
    "id": "bc497b60-c9ac-417b-abfe-78a225ca9c8c",
    "email": "example@gmail.com",
    "type": "weekly_review_view",
    "createdAt": "2026-04-14T02:25:17.975Z"
  },
  {
    "id": "3f9cceba-895a-409c-a76a-40b19c3a91e6",
    "email": "example@gmail.com",
    "type": "weekly_review_view",
    "createdAt": "2026-04-14T02:26:15.993Z"
  },
  {
    "id": "69de97cf-8bf6-4b89-a8c0-544b38cef7cd",
    "email": "example@gmail.com",
    "type": "weekly_review_view",
    "createdAt": "2026-04-14T02:27:01.316Z"
  },
  {
    "id": "e73b2faa-ada6-4b9a-8f77-565321aad983",
    "email": "example@gmail.com",
    "type": "weekly_review_view",
    "createdAt": "2026-04-14T02:31:53.317Z"
  },
  {
    "id": "cb9fc2cc-ebd4-460e-858b-bfe2de367f54",
    "email": "example@gmail.com",
    "type": "weekly_review_view",
    "createdAt": "2026-04-14T02:31:58.926Z"
  },
  {
    "id": "f01f1c6c-3d2b-4e18-aa8a-4995f0cfd673",
    "email": "example@gmail.com",
    "type": "weekly_review_view",
    "createdAt": "2026-04-14T02:31:59.932Z"
  },
  {
    "id": "84615d4b-9a73-491b-afe8-9b83ab4a9cb2",
    "email": "example@gmail.com",
    "type": "weekly_review_view",
    "createdAt": "2026-04-14T03:13:05.894Z"
  },
  {
    "id": "37ad019f-ad53-4b60-96c7-fb36264ac6fa",
    "email": "example@gmail.com",
    "type": "weekly_review_view",
    "createdAt": "2026-04-14T03:13:07.086Z"
  },
  {
    "id": "34f67168-7c21-4679-b69a-4b4862396a5e",
    "email": "example@gmail.com",
    "type": "weekly_review_view",
    "createdAt": "2026-04-14T03:13:09.861Z"
  },
  {
    "id": "865d3b36-682f-4b77-93cd-82a8c2ba8dc1",
    "email": "example@gmail.com",
    "type": "weekly_review_view",
    "createdAt": "2026-04-14T03:14:12.113Z"
  },
  {
    "id": "78077e99-3548-478d-b3a2-9d47da7757c5",
    "email": "example@gmail.com",
    "type": "weekly_review_view",
    "createdAt": "2026-04-14T03:14:46.755Z"
  },
  {
    "id": "45847326-c5b3-4f56-bbb3-bd49a454d78e",
    "email": "example@gmail.com",
    "type": "weekly_review_view",
    "createdAt": "2026-04-16T02:03:07.383Z"
  },
  {
    "id": "445314e4-596e-4eff-b544-c563f6472606",
    "email": "example@gmail.com",
    "type": "weekly_review_view",
    "createdAt": "2026-04-17T00:51:20.750Z"
  },
  {
    "id": "3a8a7b59-6491-4b1c-9871-9a68c14cab1c",
    "email": "example@gmail.com",
    "type": "weekly_review_view",
    "createdAt": "2026-04-17T01:00:11.944Z"
  },
  {
    "id": "19017378-4366-4707-a85e-51d892ce5817",
    "email": "example@gmail.com",
    "type": "weekly_review_view",
    "createdAt": "2026-04-17T01:00:11.997Z"
  },
  {
    "id": "2e089c4d-a4d6-40ec-a094-571b072a3393",
    "email": "example@gmail.com",
    "type": "weekly_review_view",
    "createdAt": "2026-04-17T01:02:29.269Z"
  },
  {
    "id": "eb842086-0158-42b4-bb92-eff13bfe79de",
    "email": "example@gmail.com",
    "type": "weekly_review_view",
    "createdAt": "2026-04-17T01:02:29.346Z"
  }
]